pyraco/__init__.py
pyraco/cli.py
pyraco/pyraco.py
pyraco-0.1.0.dist-info/LICENSE
pyraco-0.1.0.dist-info/METADATA
pyraco-0.1.0.dist-info/WHEEL
pyraco-0.1.0.dist-info/entry_points.txt
pyraco-0.1.0.dist-info/top_level.txt
pyraco-0.1.0.dist-info/RECORD
