Metadata-Version: 2.1
Name: pyraco
Version: 0.1.0
Summary: A python library for interacting with the retroarch network command interface.
Home-page: https://github.com/sopoforic/pyraco
Author: Tracy Poff
Author-email: tracy.poff@gmail.com
License: MIT license
Keywords: pyraco
Platform: UNKNOWN
Classifier: Development Status :: 2 - Pre-Alpha
Classifier: Intended Audience :: Developers
Classifier: License :: OSI Approved :: MIT License
Classifier: Natural Language :: English
Classifier: Programming Language :: Python :: 3
Classifier: Programming Language :: Python :: 3.6
Classifier: Programming Language :: Python :: 3.7
Classifier: Programming Language :: Python :: 3.8
Requires-Python: >=3.6
Requires-Dist: Click (>=7.0)
